pytensorlite/__init__.py
pytensorlite-0.1.4.dist-info/METADATA
pytensorlite-0.1.4.dist-info/WHEEL
pytensorlite-0.1.4.dist-info/top_level.txt
pytensorlite-0.1.4.dist-info/RECORD
