Metadata-Version: 2.4
Name: pytensorlite
Version: 0.1.4
Summary: Lightweight tensor utilities for Python AI modules.
Home-page: https://github.com/93dk99-ui/pytensorlite
Author: Sami Haddadi
Author-email: garnet_smitham18209@vonju.org
Classifier: Programming Language :: Python :: 3
Classifier: Operating System :: OS Independent
Classifier: Topic :: Scientific/Engineering :: Artificial Intelligence
Requires-Python: >=3.6
Dynamic: author
Dynamic: author-email
Dynamic: classifier
Dynamic: description
Dynamic: description-content-type
Dynamic: home-page
Dynamic: requires-python
Dynamic: summary
